django_cognito_auth/__init__.py
django_cognito_auth/exceptions.py
django_cognito_auth/middleware.py
django_cognito_auth/utils.py
django_cognito_auth_middleware-0.1.1.dist-info/licenses/LICENSE
django_cognito_auth_middleware-0.1.1.dist-info/METADATA
django_cognito_auth_middleware-0.1.1.dist-info/WHEEL
django_cognito_auth_middleware-0.1.1.dist-info/top_level.txt
django_cognito_auth_middleware-0.1.1.dist-info/RECORD
