Metadata-Version: 2.4
Name: django-cognito-auth-middleware
Version: 0.1.1
Summary: Reusable Django middleware for AWS Cognito authentication
Project-URL: Homepage, https://github.com/yourusername/django-cognito-auth-middleware
Requires-Python: >=3.9
License-File: LICENSE
Requires-Dist: Django>=3.2
Requires-Dist: boto3>=1.20
Dynamic: license-file
